ayoomoney/__init__.py
ayoomoney/errors.py
ayoomoney/wallet.py
ayoomoney/auth/__init__.py
ayoomoney/auth/__main__.py
ayoomoney/auth/auto.py
ayoomoney/auth/base.py
ayoomoney/auth/simple.py
ayoomoney/types/__init__.py
ayoomoney/types/account_info.py
ayoomoney/types/enums.py
ayoomoney/types/notification.py
ayoomoney/types/operation.py
ayoomoney/types/operation_details.py
ayoomoney/types/operation_history.py
ayoomoney/types/payment.py
ayoomoney/types/utils.py
ayoomoney-1.2.2.dist-info/METADATA
ayoomoney-1.2.2.dist-info/WHEEL
ayoomoney-1.2.2.dist-info/top_level.txt
ayoomoney-1.2.2.dist-info/RECORD
