Metadata-Version: 2.1
Name: ayoomoney
Version: 1.2.2
Summary: Простая синхронная/асинхронная библиотека для работы с API ЮMoney
Author-email: LazyDeus <dimaprodeus@yandex.ru>, fofmow <fofmow@gmail.com>
Project-URL: Homepage, https://github.com/Demetrous-fd/ayoomoney
Project-URL: Bug Tracker, https://github.com/Demetrous-fd/ayoomoney/issues
Classifier: Programming Language :: Python :: 3
Classifier: License :: OSI Approved :: MIT License
Classifier: Operating System :: OS Independent
Requires-Python: >=3.11
Requires-Dist: httpx~=0.23.0
Requires-Dist: pydantic~=2.0
Requires-Dist: click~=8.1
